README.rst
setup.cfg
setup.py
pyclr/__init__.py
pyclr/maps.py
pyclr/pyclr.py
pyclr/sequences.py
pyclr.egg-info/PKG-INFO
pyclr.egg-info/SOURCES.txt
pyclr.egg-info/dependency_links.txt
pyclr.egg-info/top_level.txt