Metadata-Version: 1.1
Name: pyclr
Version: 0.0.1
Summary: Easy colors in your terminal.
Home-page: https://github.com/ScottehMax/PyCLR
Author: Scott Maxwell
Author-email: scott@scotteh.me
License: MIT
Keywords: development
Platform: UNKNOWN
Classifier: Development Status :: 3 - Alpha
Classifier: Intended Audience :: Developers
Classifier: License :: OSI Approved :: MIT License
Classifier: Programming Language :: Python :: 2
Classifier: Programming Language :: Python :: 2.6
Classifier: Programming Language :: Python :: 2.7
Classifier: Programming Language :: Python :: 3
Classifier: Programming Language :: Python :: 3.2
Classifier: Programming Language :: Python :: 3.3
Classifier: Programming Language :: Python :: 3.4
